[
  {
    "key": "MDAID_神竜王女の頭飾り・金",
    "value": "Gold Divine Tiara"
  },
  {
    "key": "MDAID_H_神竜王女の頭飾り・金",
    "value": "Proof of victory over\nLegendary Ninian."
  },
  {
    "key": "MID_MISSION_M202210A_TITLE",
    "value": "Oct Quests"
  },
  {
    "key": "MID_MISSION_M202210A_A1",
    "value": "Arena Assault: Win 1"
  },
  {
    "key": "MID_MISSION_H_M202210A_A1",
    "value": "Win one battle in Arena Assault."
  },
  {
    "key": "MID_MISSION_M202210A_A2",
    "value": "Arena Assault: 3 in a Row"
  },
  {
    "key": "MID_MISSION_H_M202210A_A2",
    "value": "Win three consecutive battles\nin Arena Assault."
  },
  {
    "key": "MID_MISSION_M202210A_A3",
    "value": "Arena Assault: 5 in a Row"
  },
  {
    "key": "MID_MISSION_H_M202210A_A3",
    "value": "Win five consecutive battles\nin Arena Assault."
  },
  {
    "key": "MID_MISSION_M202210A_A4",
    "value": "KO w/Alfonse"
  },
  {
    "key": "MID_MISSION_H_M202210A_A4",
    "value": "Defeat a foe with Alfonse: Prince of Askr."
  },
  {
    "key": "MID_MISSION_M202210A_A5",
    "value": "KO w/Sharena"
  },
  {
    "key": "MID_MISSION_H_M202210A_A5",
    "value": "Defeat a foe with Sharena: Princess of Askr."
  },
  {
    "key": "MID_MISSION_M202210A_A6",
    "value": "KO w/Anna"
  },
  {
    "key": "MID_MISSION_H_M202210A_A6",
    "value": "Defeat a foe with Anna: Commander."
  },
  {
    "key": "MID_MISSION_M202210A_A7",
    "value": "KO Red Foe"
  },
  {
    "key": "MID_MISSION_H_M202210A_A7",
    "value": "Defeat a red foe."
  },
  {
    "key": "MID_MISSION_M202210A_A8",
    "value": "KO Blue Foe"
  },
  {
    "key": "MID_MISSION_H_M202210A_A8",
    "value": "Defeat a blue foe."
  },
  {
    "key": "MID_MISSION_M202210A_A9",
    "value": "KO Green Foe"
  },
  {
    "key": "MID_MISSION_H_M202210A_A9",
    "value": "Defeat a green foe."
  },
  {
    "key": "MID_MISSION_M202210A_A10",
    "value": "KO Colorless Foe"
  },
  {
    "key": "MID_MISSION_H_M202210A_A10",
    "value": "Defeat a colorless foe."
  },
  {
    "key": "MID_MISSION_M202210A_A11",
    "value": "KO Infantry Foe"
  },
  {
    "key": "MID_MISSION_H_M202210A_A11",
    "value": "Defeat an infantry foe."
  },
  {
    "key": "MID_MISSION_M202210A_A12",
    "value": "KO Armored Foe"
  },
  {
    "key": "MID_MISSION_H_M202210A_A12",
    "value": "Defeat an armored foe."
  },
  {
    "key": "MID_MISSION_M202210A_A13",
    "value": "KO Cavalry Foe"
  },
  {
    "key": "MID_MISSION_H_M202210A_A13",
    "value": "Defeat a cavalry foe."
  },
  {
    "key": "MID_MISSION_M202210A_A14",
    "value": "KO Flying Foe"
  },
  {
    "key": "MID_MISSION_H_M202210A_A14",
    "value": "Defeat a flying foe."
  },
  {
    "key": "MID_MISSION_M202210A_A15",
    "value": "Clear 7-1"
  },
  {
    "key": "MID_MISSION_H_M202210A_A15",
    "value": "Clear Book V, Chapter 7: Part 1 on Lunatic\ndifficulty. All four allies must survive."
  },
  {
    "key": "MID_MISSION_M202210A_A16",
    "value": "Clear 7-2"
  },
  {
    "key": "MID_MISSION_H_M202210A_A16",
    "value": "Clear Book V, Chapter 7: Part 2 on Lunatic\ndifficulty. All four allies must survive."
  },
  {
    "key": "MID_MISSION_M202210A_A17",
    "value": "Clear 7-3"
  },
  {
    "key": "MID_MISSION_H_M202210A_A17",
    "value": "Clear Book V, Chapter 7: Part 3 on Lunatic\ndifficulty. All four allies must survive."
  },
  {
    "key": "MID_MISSION_M202210A_A18",
    "value": "Clear 7-4"
  },
  {
    "key": "MID_MISSION_H_M202210A_A18",
    "value": "Clear Book V, Chapter 7: Part 4 on Lunatic\ndifficulty. All four allies must survive."
  },
  {
    "key": "MID_MISSION_M202210A_A19",
    "value": "Clear 7-5"
  },
  {
    "key": "MID_MISSION_H_M202210A_A19",
    "value": "Clear Book V, Chapter 7: Part 5 on Lunatic\ndifficulty. All four allies must survive."
  },
  {
    "key": "MID_MISSION_M202210A_A20",
    "value": "AR: Attack Successfully"
  },
  {
    "key": "MID_MISSION_H_M202210A_A20",
    "value": "Successfully attack in Aether Raids."
  },
  {
    "key": "MID_MISSION_M202210A_A21",
    "value": "AR: Attack Successfully"
  },
  {
    "key": "MID_MISSION_H_M202210A_A21",
    "value": "Successfully attack in Aether Raids."
  },
  {
    "key": "MID_MISSION_M202210A_A22",
    "value": "AR: Attack Successfully"
  },
  {
    "key": "MID_MISSION_H_M202210A_A22",
    "value": "Successfully attack in Aether Raids."
  },
  {
    "key": "MID_MISSION_M202210A_A23",
    "value": "Win Arena Duel"
  },
  {
    "key": "MID_MISSION_H_M202210A_A23",
    "value": "Win Arena Duel at any difficulty."
  },
  {
    "key": "MID_MISSION_M202210A_A24",
    "value": "Win Arena Duel"
  },
  {
    "key": "MID_MISSION_H_M202210A_A24",
    "value": "Win Arena Duel at any difficulty."
  },
  {
    "key": "MID_MISSION_M202210A_A25",
    "value": "Win Arena Duel"
  },
  {
    "key": "MID_MISSION_H_M202210A_A25",
    "value": "Win Arena Duel at any difficulty."
  },
  {
    "key": "MID_MISSION_S202209VOTE01_TITLE",
    "value": "Voting Gauntlet"
  },
  {
    "key": "MID_MISSION_S202209VOTE01_A1",
    "value": "Voting Gauntlet"
  },
  {
    "key": "MID_MISSION_H_S202209VOTE01_A1",
    "value": "Win a battle in the Voting Gauntlet."
  },
  {
    "key": "MID_MISSION_S202209VOTE01_A2",
    "value": "Voting Gauntlet"
  },
  {
    "key": "MID_MISSION_H_S202209VOTE01_A2",
    "value": "Win a battle in the Voting Gauntlet."
  },
  {
    "key": "MID_MISSION_S202209VOTE01_A3",
    "value": "Voting Gauntlet"
  },
  {
    "key": "MID_MISSION_H_S202209VOTE01_A3",
    "value": "Win a battle in the Voting Gauntlet."
  },
  {
    "key": "MID_MISSION_S202209VOTE01_A4",
    "value": "Voting Gauntlet"
  },
  {
    "key": "MID_MISSION_H_S202209VOTE01_A4",
    "value": "Win a battle in the Voting Gauntlet."
  },
  {
    "key": "MID_MISSION_S202209VOTE01_A5",
    "value": "Voting Gauntlet"
  },
  {
    "key": "MID_MISSION_H_S202209VOTE01_A5",
    "value": "Win a battle in the Voting Gauntlet."
  },
  {
    "key": "MID_MISSION_S202209VOTE01_A6",
    "value": "Tower: 2nd Stratum"
  },
  {
    "key": "MID_MISSION_H_S202209VOTE01_A6",
    "value": "Clear the second stratum of the Training Tower."
  },
  {
    "key": "MID_MISSION_S202209VOTE01_A7",
    "value": "Tower: 5th Stratum"
  },
  {
    "key": "MID_MISSION_H_S202209VOTE01_A7",
    "value": "Clear the fifth stratum of the Training Tower."
  },
  {
    "key": "MID_MISSION_S202209VOTE01_A8",
    "value": "Tower: 8th Stratum"
  },
  {
    "key": "MID_MISSION_H_S202209VOTE01_A8",
    "value": "Clear the eighth stratum of the Training Tower."
  },
  {
    "key": "MID_MISSION_S202209VOTE01_A9",
    "value": "Win Arena Duels"
  },
  {
    "key": "MID_MISSION_H_S202209VOTE01_A9",
    "value": "Win Arena Duels at any difficulty."
  },
  {
    "key": "MID_MISSION_S202209VOTE01_A10",
    "value": "Win Arena Duels"
  },
  {
    "key": "MID_MISSION_H_S202209VOTE01_A10",
    "value": "Win Arena Duels at any difficulty."
  },
  {
    "key": "MID_MISSION_S202209VOTE01_A11",
    "value": "Win Int.+ Arena Duels"
  },
  {
    "key": "MID_MISSION_H_S202209VOTE01_A11",
    "value": "Win Arena Duels on Intermediate or higher\ndifficulty."
  },
  {
    "key": "MID_MISSION_S202209VOTE01_A12",
    "value": "Win Int.+ Arena Duels"
  },
  {
    "key": "MID_MISSION_H_S202209VOTE01_A12",
    "value": "Win Arena Duels on Intermediate or higher\ndifficulty."
  },
  {
    "key": "MID_MISSION_S202209VOTE01_A13",
    "value": "Voting Gauntlet"
  },
  {
    "key": "MID_MISSION_H_S202209VOTE01_A13",
    "value": "Win a battle in the Voting Gauntlet with a red\nally on your team."
  },
  {
    "key": "MID_MISSION_S202209VOTE01_A14",
    "value": "Voting Gauntlet"
  },
  {
    "key": "MID_MISSION_H_S202209VOTE01_A14",
    "value": "Win a battle in the Voting Gauntlet with a blue\nally on your team."
  },
  {
    "key": "MID_MISSION_S202209VOTE01_A15",
    "value": "Voting Gauntlet"
  },
  {
    "key": "MID_MISSION_H_S202209VOTE01_A15",
    "value": "Win a battle in the Voting Gauntlet with a green\nally on your team."
  },
  {
    "key": "MID_MISSION_S202209VOTE01_A16",
    "value": "Voting Gauntlet"
  },
  {
    "key": "MID_MISSION_H_S202209VOTE01_A16",
    "value": "Win a battle in the Voting Gauntlet with a\ncolorless ally on your team."
  },
  {
    "key": "MID_MISSION_S202209VOTE01_A17",
    "value": "Voting Gauntlet"
  },
  {
    "key": "MID_MISSION_H_S202209VOTE01_A17",
    "value": "Win a battle in the Voting Gauntlet with a red\nally on your team."
  },
  {
    "key": "MID_MISSION_S202209VOTE01_A18",
    "value": "Voting Gauntlet"
  },
  {
    "key": "MID_MISSION_H_S202209VOTE01_A18",
    "value": "Win a battle in the Voting Gauntlet with a blue\nally on your team."
  },
  {
    "key": "MID_MISSION_S202209VOTE01_A19",
    "value": "Voting Gauntlet"
  },
  {
    "key": "MID_MISSION_H_S202209VOTE01_A19",
    "value": "Win a battle in the Voting Gauntlet with a green\nally on your team."
  },
  {
    "key": "MID_MISSION_S202209VOTE01_A20",
    "value": "Voting Gauntlet"
  },
  {
    "key": "MID_MISSION_H_S202209VOTE01_A20",
    "value": "Win a battle in the Voting Gauntlet with a\ncolorless ally on your team."
  },
  {
    "key": "MID_MISSION_S202209VOTE01_A21",
    "value": "Voting Gauntlet"
  },
  {
    "key": "MID_MISSION_H_S202209VOTE01_A21",
    "value": "Win a battle in the Voting Gauntlet with a red\nally on your team."
  },
  {
    "key": "MID_MISSION_S202209VOTE01_A22",
    "value": "Voting Gauntlet"
  },
  {
    "key": "MID_MISSION_H_S202209VOTE01_A22",
    "value": "Win a battle in the Voting Gauntlet with a blue\nally on your team."
  },
  {
    "key": "MID_MISSION_S202209VOTE01_A23",
    "value": "Voting Gauntlet"
  },
  {
    "key": "MID_MISSION_H_S202209VOTE01_A23",
    "value": "Win a battle in the Voting Gauntlet with a green\nally on your team."
  },
  {
    "key": "MID_MISSION_S202209VOTE01_A24",
    "value": "Voting Gauntlet"
  },
  {
    "key": "MID_MISSION_H_S202209VOTE01_A24",
    "value": "Win a battle in the Voting Gauntlet with a\ncolorless ally on your team."
  },
  {
    "key": "MID_MISSION_S202210CHARA01_TITLE",
    "value": "Three Heroes"
  },
  {
    "key": "MID_MISSION_S202210CHARA01_A1",
    "value": "KO Foe"
  },
  {
    "key": "MID_MISSION_H_S202210CHARA01_A1",
    "value": "Defeat an enemy."
  },
  {
    "key": "MID_MISSION_S202210CHARA01_A2",
    "value": "KO with Titania"
  },
  {
    "key": "MID_MISSION_H_S202210CHARA01_A2",
    "value": "Defeat a foe with Titania: Mighty Mercenary."
  },
  {
    "key": "MID_MISSION_S202210CHARA01_A3",
    "value": "KO with Seth"
  },
  {
    "key": "MID_MISSION_H_S202210CHARA01_A3",
    "value": "Defeat a foe with Seth: Silver Knight."
  },
  {
    "key": "MID_MISSION_S202210CHARA01_B1",
    "value": "KO Lvl. 20+ Foe"
  },
  {
    "key": "MID_MISSION_H_S202210CHARA01_B1",
    "value": "Defeat a foe that is level 20 or higher\nwith Titania: Mighty Mercenary."
  },
  {
    "key": "MID_MISSION_S202210CHARA01_B2",
    "value": "KO Lvl. 20+ Foe"
  },
  {
    "key": "MID_MISSION_H_S202210CHARA01_B2",
    "value": "Defeat a foe that is level 20 or higher\nwith Seth: Silver Knight."
  },
  {
    "key": "MID_MISSION_S202210CHARA01_B3",
    "value": "KO Lvl. 20+ Foe"
  },
  {
    "key": "MID_MISSION_H_S202210CHARA01_B3",
    "value": "Defeat a foe that is level 20 or higher\nwith Merlinus: Pherae's Clerk."
  },
  {
    "key": "MID_MISSION_S202210CHARA01_C1",
    "value": "KO Lvl. 35+ Foe"
  },
  {
    "key": "MID_MISSION_H_S202210CHARA01_C1",
    "value": "Defeat a foe that is level 35 or higher\nwith Titania: Mighty Mercenary."
  },
  {
    "key": "MID_MISSION_S202210CHARA01_C2",
    "value": "KO Lvl. 35+ Foe"
  },
  {
    "key": "MID_MISSION_H_S202210CHARA01_C2",
    "value": "Defeat a foe that is level 35 or higher\nwith Seth: Silver Knight."
  },
  {
    "key": "MID_MISSION_S202210CHARA01_C3",
    "value": "KO Lvl. 35+ Foe"
  },
  {
    "key": "MID_MISSION_H_S202210CHARA01_C3",
    "value": "Defeat a foe that is level 35 or higher\nwith Merlinus: Pherae's Clerk."
  },
  {
    "key": "MID_MISSION_S202210HERO01_TITLE",
    "value": "Grand Hero Battles"
  },
  {
    "key": "MID_MISSION_S202210HERO01_A1",
    "value": "Defeat Aelfric"
  },
  {
    "key": "MID_MISSION_H_S202210HERO01_A1",
    "value": "Clear the Grand Hero Battle against Aelfric:\nCustodian Monk with Sharena: Princess of\nAskr on your team."
  },
  {
    "key": "MID_MISSION_S202210HERO01_A2",
    "value": "Defeat Aelfric"
  },
  {
    "key": "MID_MISSION_H_S202210HERO01_A2",
    "value": "Clear the Grand Hero Battle against Aelfric:\nCustodian Monk on Lunatic or higher difficulty\nwith Aelfric: Custodian Monk on your team."
  },
  {
    "key": "MID_MISSION_S202210HERO01_A3",
    "value": "Defeat Aelfric"
  },
  {
    "key": "MID_MISSION_H_S202210HERO01_A3",
    "value": "Defeat Aelfric: Custodian Monk at level 40\nor higher with Sharena: Princess of Askr."
  },
  {
    "key": "MID_MISSION_S202210HERO01_A4",
    "value": "Defeat Aelfric"
  },
  {
    "key": "MID_MISSION_H_S202210HERO01_A4",
    "value": "Defeat Aelfric: Custodian Monk at level 40\nor higher with Aelfric: Custodian Monk."
  },
  {
    "key": "MID_MISSION_S202210HERO01_A5",
    "value": "Defeat Aelfric"
  },
  {
    "key": "MID_MISSION_H_S202210HERO01_A5",
    "value": "Clear the Grand Hero Battle against Aelfric:\nCustodian Monk on Lunatic or higher with\nan all-armored team."
  },
  {
    "key": "MID_MISSION_S202210MJOLNIR01_TITLE",
    "value": "Mjölnir's Strike"
  },
  {
    "key": "MID_MISSION_S202210MJOLNIR01_A1",
    "value": "KO w/Summoner"
  },
  {
    "key": "MID_MISSION_H_S202210MJOLNIR01_A1",
    "value": "Defeat a foe with the My Summoner unit\nin Mjölnir's Strike."
  },
  {
    "key": "MID_MISSION_S202210MJOLNIR01_A2",
    "value": "KO w/Summoner"
  },
  {
    "key": "MID_MISSION_H_S202210MJOLNIR01_A2",
    "value": "Defeat a foe with the My Summoner unit\nin Mjölnir's Strike."
  },
  {
    "key": "MID_MISSION_W_M202210B_TITLE",
    "value": "Oct Training"
  },
  {
    "key": "MID_MISSION_W_M202210B_A1",
    "value": "Tower: 1st Stratum"
  },
  {
    "key": "MID_MISSION_H_W_M202210B_A1",
    "value": "Clear the first stratum of the Training Tower.\nAll four allies must survive."
  },
  {
    "key": "MID_MISSION_W_M202210B_A2",
    "value": "Tower: 2nd Stratum"
  },
  {
    "key": "MID_MISSION_H_W_M202210B_A2",
    "value": "Clear the second stratum of the Training Tower.\nAll four allies must survive."
  },
  {
    "key": "MID_MISSION_W_M202210B_A3",
    "value": "Tower: 3rd Stratum"
  },
  {
    "key": "MID_MISSION_H_W_M202210B_A3",
    "value": "Clear the third stratum of the Training Tower.\nAll four allies must survive."
  },
  {
    "key": "MID_MISSION_W_M202210B_A4",
    "value": "Tower: 4th Stratum"
  },
  {
    "key": "MID_MISSION_H_W_M202210B_A4",
    "value": "Clear the fourth stratum of the Training Tower.\nAll four allies must survive."
  },
  {
    "key": "MID_MISSION_W_M202210B_A5",
    "value": "Tower: 5th Stratum"
  },
  {
    "key": "MID_MISSION_H_W_M202210B_A5",
    "value": "Clear the fifth stratum of the Training Tower.\nAll four allies must survive."
  },
  {
    "key": "MID_MISSION_W_M202210B_A6",
    "value": "Tower: 6th Stratum"
  },
  {
    "key": "MID_MISSION_H_W_M202210B_A6",
    "value": "Clear the sixth stratum of the Training Tower.\nAll four allies must survive."
  },
  {
    "key": "MID_MISSION_W_M202210B_A7",
    "value": "Tower: 7th Stratum"
  },
  {
    "key": "MID_MISSION_H_W_M202210B_A7",
    "value": "Clear the seventh stratum of the Training\nTower. All four allies must survive."
  },
  {
    "key": "MID_MISSION_W_M202210B_A8",
    "value": "Tower: 8th Stratum"
  },
  {
    "key": "MID_MISSION_H_W_M202210B_A8",
    "value": "Clear the eighth stratum of the Training Tower.\nAll four allies must survive."
  },
  {
    "key": "MID_MISSION_W_M202210B_A9",
    "value": "Tower: 9th Stratum"
  },
  {
    "key": "MID_MISSION_H_W_M202210B_A9",
    "value": "Clear the ninth stratum of the Training Tower.\nAll four allies must survive."
  },
  {
    "key": "MID_MISSION_W_M202210B_A10",
    "value": "Tower: 10th Stratum"
  },
  {
    "key": "MID_MISSION_H_W_M202210B_A10",
    "value": "Clear the tenth stratum of the Training Tower.\nAll four allies must survive."
  },
  {
    "key": "MID_MISSION_W_M202210B_A11",
    "value": "Tower: 10th Stratum"
  },
  {
    "key": "MID_MISSION_H_W_M202210B_A11",
    "value": "Clear the tenth stratum of the Training Tower\nusing only infantry allies. (Allies deployed as\ncohorts using Pair Up do not count.) All four\nallies must survive."
  },
  {
    "key": "MID_MISSION_W_M202210B_A12",
    "value": "Tower: 10th Stratum"
  },
  {
    "key": "MID_MISSION_H_W_M202210B_A12",
    "value": "Clear the tenth stratum of the Training Tower\nusing only armored allies. (Allies deployed as\ncohorts using Pair Up do not count.) All four\nallies must survive."
  },
  {
    "key": "MID_MISSION_W_M202210B_A13",
    "value": "Tower: 10th Stratum"
  },
  {
    "key": "MID_MISSION_H_W_M202210B_A13",
    "value": "Clear the tenth stratum of the Training Tower\nusing only cavalry allies. (Allies deployed as\ncohorts using Pair Up do not count.) All four\nallies must survive."
  },
  {
    "key": "MID_MISSION_W_M202210B_A14",
    "value": "Tower: 10th Stratum"
  },
  {
    "key": "MID_MISSION_H_W_M202210B_A14",
    "value": "Clear the tenth stratum of the Training Tower\nusing only flying allies. (Allies deployed as\ncohorts using Pair Up do not count.) All four\nallies must survive."
  },
  {
    "key": "MPID_伝承ニニアン",
    "value": "Ninian"
  },
  {
    "key": "MPID_SEARCH_伝承ニニアン",
    "value": "Ninian"
  },
  {
    "key": "MPID_HONOR_伝承ニニアン",
    "value": "Ice-Dragon Oracle"
  },
  {
    "key": "MPID_H_伝承ニニアン",
    "value": "An ice dragon in human form, who lost her life\nat the hands of the man she loved. Resurrected,\nshe now lives alongside mortals. Appears in Fire\nEmblem: The Blazing Blade."
  },
  {
    "key": "MPID_VOICE_伝承ニニアン",
    "value": "Brianna Knickerbocker"
  },
  {
    "key": "MPID_ILLUST_伝承ニニアン",
    "value": "azu‐taro (azuタロウ)"
  },
  {
    "key": "MPID_LEGEND_伝承ニニアン",
    "value": "Legendary Effect: Water\nAlly Boost: HP+3, Res+4\n\nGrants allies this Legendary Effect during Water\nseason, if the Water blessing has been conferred\nand if this unit enters battle with them.\n\nStandard Effect 1: Duel\nIf unit is 5★ and level 40 and unit's stats total\nless than 190, treats unit's stats as 190 in\nmodes like Arena. (Higher-scoring opponents\nwill appear. Stat total calculation excludes any\nvalues added by merges and skills.)\nStandard Effect 2: Pair Up\nAn ability that can only be used under certain\ncircumstances. Pair Up can be accessed from\nthe Interact with Allies menu, and allows this\nunit to join battle in a group with another ally."
  },
  {
    "key": "MID_TIPS_Summon_v0609c_legend_01_伝承ニニアン",
    "value": "Can effectively perform another\naction after granting one to an ally.\nStrong, particularly against blue!"
  },
  {
    "key": "MSID_神舞のブレス",
    "value": "Faithful Breath"
  },
  {
    "key": "MSID_SEARCH_神舞のブレス",
    "value": "Faithful Breath"
  },
  {
    "key": "MSID_尊き竜の血を継ぐ娘",
    "value": "Dragon's Dance"
  },
  {
    "key": "MSID_SEARCH_尊き竜の血を継ぐ娘",
    "value": "Dragon's Dance"
  },
  {
    "key": "MSID_H_神舞のブレス",
    "value": "$aGrants Atk+3. If Sing or Dance is used, inflicts\nDef/Res-6 on nearest foes within 4 spaces of\nboth unit and target ally through their next\nactions. At start of combat, if unit's HP ≥ 40%,\ngrants Atk/Spd+6 to unit during combat, and\nalso, if unit initiates combat, neutralizes effects\nthat prevent unit's follow-up attacks, and also,\nif unit initiates combat and has weapon-triangle\nadvantage or【Penalty】is active on foe,\nfoe cannot counterattack. If foe's Range = 2,\ncalculates damage using the lower of foe's\nDef or Res.\n\n【Penalty】\nAll effects that last \"on foe through its next\naction.\" Includes penalties inflicted by a skill\nlike Panic or Threaten and negative status\neffects (preventing counterattacks, restricting\nmovement, or the effects of a skill like\nTriangle Adept or Guard)."
  },
  {
    "key": "MSID_H_尊き竜の血を継ぐ娘",
    "value": "$aGrants another action to target ally. If used\non turn 2 onward, also grants another action\nto unit, grants Atk/Spd+6 to unit and Pair Up\ncohort (if any) for 1 turn, and inflicts【Isolation】\non unit and Pair Up cohort (if any) through their\nnext action. (Effects that can trigger on turn 2\nonward will not trigger again for 3 turns after\ntriggering. Cannot target an ally with Sing or\nDance. This skill treated as Sing or Dance.)\n\n【Isolation】\nTarget cannot use or be the target of Assist\nskills through its next action. (Target can\nneither use nor be the target of skills like\nDance and Sing, skills that neutralize penalties,\nlike Restore and Harsh Command+, etc.)"
  },
  {
    "key": "MID_STAGE_HONOR_L0055",
    "value": "Ice-Dragon Oracle"
  },
  {
    "key": "MID_STAGE_L0055",
    "value": "Ninian"
  },
  {
    "key": "MID_STAGE_TITLE_PB168",
    "value": "Skill Studies 168"
  },
  {
    "key": "MID_STAGE_PB168",
    "value": "Oracle Resurrected"
  }
]