[
  {
    "key": "MID_CECILIA_HOME1",
    "value": "Comandante Anna parece ser uma\nótima instrutora. Meus métodos são\ndiferentes, mas vamos nos dar bem."
  },
  {
    "key": "MID_CECILIA_HOME2",
    "value": "Fui professora de Roy e Lilina,\ndois de meus alunos favoritos.\nAmbos adoráveis."
  },
  {
    "key": "MID_CECILIA_HOME3",
    "value": "Ser o estrategista daqui deve ser\ndesgastante. Se quiser tomar chá\nalgum dia, adoraria acompanhar você."
  },
  {
    "key": "MID_CECILIA_HOME4",
    "value": "Você é $Go,a| estrategista e eu, uma arma\nao seu dispor. Nossa amizade nunca\nperturbará a hierarquia de comando."
  },
  {
    "key": "MID_CECILIA_HOME5",
    "value": "Embora eu tenha ensinado a arte da\nbatalha a outros, como Roy, adoraria\naprender o que você puder ensinar."
  },
  {
    "key": "MID_CECILIA_FRIEND",
    "value": "Como vai? Presumo que você\nseja $Nu?$k$pSou Cecilia, vim cumprimentá-$Glo,la|."
  },
  {
    "key": "MID_CECILIA_LEVEL1",
    "value": "Que maravilha\nter ganhos notáveis!"
  },
  {
    "key": "MID_CECILIA_LEVEL2",
    "value": "Qualquer melhoria é bem-vinda."
  },
  {
    "key": "MID_CECILIA_LEVEL3",
    "value": "Nesse ritmo, talvez eu tenha que\nrenunciar ao meu título."
  },
  {
    "key": "MID_CECILIA_SKILL",
    "value": "Você escolheu conceder isso a mim.\nVou fazer jus a suas expectativas."
  },
  {
    "key": "MID_CECILIA_JOIN",
    "value": "Eu sou Cecilia, a maga general\nde Etrúria. Você é $Go,a| estrategista?\nPrazer em conhecê-l$Go,a|."
  },
  {
    "key": "MID_CECILIA_STRONGEST",
    "value": "Quando conheci você, minha\nintenção era lhe ensinar tanto\nquanto ensinei a Roy e Lilina.$k$pMas então vi como você cresceu\nrápido em seu papel aqui, tanto que\nultrapassou até mesmo a mim.$k$pÉ o momento amargo e ao mesmo\ntempo feliz, pelo qual todo professor\npassa:$k$pQuando nossos alunos nos\nultrapassam e aprendem a voar.$k$pÉ o momento em que nos sentimos\ndeixados para trás...$k$pO quê? Você ainda precisa de mim?\nÉ um alívio ouvir isso. Talvez\neu ainda tenha o que ensinar.$k$pBem, está resolvido. Ficarei\npor aqui, então!"
  },
  {
    "key": "MID_CECILIA_VOICE01",
    "value": "はっ！"
  },
  {
    "key": "MID_CECILIA_VOICE02",
    "value": "はぁっ！"
  },
  {
    "key": "MID_CECILIA_VOICE03",
    "value": "きゃああっ！"
  },
  {
    "key": "MID_CECILIA_VOICE04",
    "value": "I let my guard down..."
  },
  {
    "key": "MID_CECILIA_VOICE05",
    "value": "Aqui e agora!"
  },
  {
    "key": "MID_CECILIA_VOICE06",
    "value": "Nunca me subestime!"
  },
  {
    "key": "MID_CECILIA_VOICE07",
    "value": "Afaste-se de mim!"
  },
  {
    "key": "MID_CECILIA_VOICE08",
    "value": "Essa é a minha chance!"
  },
  {
    "key": "MID_CECILIA_VOICE09",
    "value": "The light..."
  },
  {
    "key": "MID_CECILIA_VOICE10",
    "value": "Heehee"
  },
  {
    "key": "MID_CECILIA_VOICE11",
    "value": "How fare you, tactician?"
  },
  {
    "key": "MID_CECILIA_VOICE12",
    "value": "Now, now... No need to nudge me. You have my attention."
  },
  {
    "key": "MID_CECILIA_VOICE13",
    "value": "I sense a great deal of talent in you. You're a natural."
  },
  {
    "key": "MID_CECILIA_VOICE14",
    "value": "Shall we discuss battle strategy?\n"
  },
  {
    "key": "MID_CECILIA_VOICE15",
    "value": "Should you wish to know anything at all, simply ask!"
  },
  {
    "key": "MID_CECILIA_VOICE16",
    "value": "I will ever do my best to fulfill my role."
  },
  {
    "key": "MID_CECILIA_VOICE17",
    "value": "You have much to teach, and even I have much to learn."
  },
  {
    "key": "MID_CECILIA_VOICE18",
    "value": "Mm-hmm?"
  },
  {
    "key": "MID_CECILIA_VOICE19",
    "value": "Yes?"
  },
  {
    "key": "MID_CECILIA_VOICE20",
    "value": "Your orders."
  }
]