[
  {
    "key": "MID_SCENARIO_OPENING_BGM",
    "value": "BGM_MNS_FE03_02"
  },
  {
    "key": "MID_SCENARIO_OPENING_IMAGE",
    "value": "BG_Blank_White"
  },
  {
    "key": "MID_SCENARIO_OPENING",
    "value": "$Fo500,255,255,255,255|$bEvBg_EmbraAnotherThrone_before|$Fi2000|$WmMEID_エルム,ch00_40_Elm_M_Normal,Face_Cool|Lady Embla! Você está bem?$k$p$WmMPID_エンブラ,ch00_43_Embla_Normal,Face_Pain|...$k$p$WmMEID_エルム,ch00_40_Elm_M_Normal,Face_Pain|Isso é... Sangue de mortais?$k$p$WmMPID_エンブラ,ch00_43_Embla_Normal,Face_Pain|Eu o matei...$k$pNão era a minha intenção. Ele veio\naté mim sorrindo, ele queria fazer um\ntributo...$k$pEntão por que ele... Veio na minha\ndireção com medo nos seus olhos?$k$pPor que... Ele tentou me matar?$k$p$WmMEID_エルム,ch00_40_Elm_M_Normal,Face_Pain|Esta é a natureza dos mortais, lady\nEmbla...$k$p$EFace_Anger|Se o seu sangue pode lhes dar poder,\nentão com certeza, eles pensam, se\npuderem tirar a sua vida...$k$p$EFace_Cool|A fome de poder. É por isso que eles\no traem tão facilmente... Até quando\neles devem tudo que têm a você.$k$p$WmMPID_エンブラ,ch00_43_Embla_Normal,Face_Pain|...$k$p$Sbs2000|$Fo2000,255,255,255,255|"
  },
  {
    "key": "MID_SCENARIO_MAP_BEGIN_BGM",
    "value": "BGM_EVENT_PLAIN_01"
  },
  {
    "key": "MID_SCENARIO_MAP_BEGIN",
    "value": "$WmMPID_ハーディン,ch01_29_Hardin_M_Normal,Face|Princesa Nyna... Juro que sempre a\nprotegerei.$k$p$Sbs1000|"
  }
]