[
  {
    "key": "MID_JAFFAR_HOME1",
    "value": "\"Orden de Héroes\"... Qué raro\nsuena. ¿Cuál es su objetivo?\n¿Matar en nombre de su patria?"
  },
  {
    "key": "MID_JAFFAR_HOME2",
    "value": "Se podría decir que en mi mundo\nfui un cadáver andante desde el\ndía en que nací.$k$pPero entonces conocí a Nino...\ny mi vida cambió."
  },
  {
    "key": "MID_JAFFAR_HOME3",
    "value": "¿De patrulla otra vez? Bien hecho:\nno hay mejor manera para detectar\na espías y asesinos."
  },
  {
    "key": "MID_JAFFAR_HOME4",
    "value": "¿Vienes a hablar conmigo?\nSupongo que querrás algún\nconsejo profesional.$k$pBien, pues apunta: el momento\nmás indicado para asesinar a\nalguien es cuando está durmiendo."
  },
  {
    "key": "MID_JAFFAR_HOME5",
    "value": "Siempre que tengo un momento\npara meditar, pienso en asesinar\na alguien.$k$pSé que suena terrible, pero llevo\nhaciéndolo desde la infancia."
  },
  {
    "key": "MID_JAFFAR_FRIEND",
    "value": "No huyas. No vine a matarte,\nsino a traerte saludos de parte\nde $Nf."
  },
  {
    "key": "MID_JAFFAR_LEVEL1",
    "value": "Fue solo suerte."
  },
  {
    "key": "MID_JAFFAR_LEVEL2",
    "value": "Aceptable."
  },
  {
    "key": "MID_JAFFAR_LEVEL3",
    "value": "Me falta práctica."
  },
  {
    "key": "MID_JAFFAR_SKILL",
    "value": "¿Me ayudará esto a derramar\nmás sangre?"
  },
  {
    "key": "MID_JAFFAR_JOIN",
    "value": "Soy Jaffar, conocido como el Ángel\nMortal por los miembros del Colmillo\nNegro. Y ahora también por ti."
  },
  {
    "key": "MID_JAFFAR_STRONGEST",
    "value": "Nos tratas con demasiada amabilidad.\nA mí, a los demás compañeros...\nEn fin, a todo el mundo.$k$pEse es tu único punto débil,\n$Nu.$k$pEspero que no me consideres un\namigo, porque cometerías un grave\nerror. Solo soy un arma mortífera.$k$pSi alguna vez dejo de resultarte útil,\ndebes deshacerte de mí como si\nfuera basura. Por duro que te resulte.$k$p¿Qué? ¿Dices que te niegas? En ese\ncaso... no me dejas otra opción que\nprometerte mi lealtad más absoluta.$k$pDebes saber que por ti estoy\ndispuesto a acometer cualquier\nmisión, no importa cuán cruel.$k$pY te aseguro que, cuando la\ncumpla, volveré a tu lado.\nSin dudarlo un solo instante."
  },
  {
    "key": "MID_JAFFAR_VOICE01",
    "value": "はっ"
  },
  {
    "key": "MID_JAFFAR_VOICE02",
    "value": "ふっ"
  },
  {
    "key": "MID_JAFFAR_VOICE03",
    "value": "うああっ！"
  },
  {
    "key": "MID_JAFFAR_VOICE04",
    "value": "Damn...nngh...\n"
  },
  {
    "key": "MID_JAFFAR_VOICE05",
    "value": "La muerte acecha."
  },
  {
    "key": "MID_JAFFAR_VOICE06",
    "value": "Se acabó."
  },
  {
    "key": "MID_JAFFAR_VOICE07",
    "value": "Otra víctima..."
  },
  {
    "key": "MID_JAFFAR_VOICE08",
    "value": "Tu fin se acerca."
  },
  {
    "key": "MID_JAFFAR_VOICE09",
    "value": "It ends..."
  },
  {
    "key": "MID_JAFFAR_VOICE10",
    "value": "Huh."
  },
  {
    "key": "MID_JAFFAR_VOICE11",
    "value": "Next mission. Please."
  },
  {
    "key": "MID_JAFFAR_VOICE12",
    "value": "The human touch? Not for me."
  },
  {
    "key": "MID_JAFFAR_VOICE13",
    "value": "I am known as the Angel of Death."
  },
  {
    "key": "MID_JAFFAR_VOICE14",
    "value": "Do I know of...joy, sorrow, anger, dread? No."
  },
  {
    "key": "MID_JAFFAR_VOICE15",
    "value": "I have...no heart."
  },
  {
    "key": "MID_JAFFAR_VOICE16",
    "value": "A pile of corpses. Upon that I was born. An infant in a cradle of death."
  },
  {
    "key": "MID_JAFFAR_VOICE17",
    "value": "You must...live."
  },
  {
    "key": "MID_JAFFAR_VOICE18",
    "value": "Hmmm."
  },
  {
    "key": "MID_JAFFAR_VOICE19",
    "value": "Orders?"
  },
  {
    "key": "MID_JAFFAR_VOICE20",
    "value": "Yes."
  }
]