[
  {
    "key": "MID_MARC_M_HOME1",
    "value": "Your white robe is too cool! But I'd\nexpect nothing less from the tactician\nof the Order of Heroes. Say, can we...$k$pSwap robes? Just for a moment?!"
  },
  {
    "key": "MID_MARC_M_HOME2",
    "value": "I have no memories of my previous\nworld. All I remember is my name,\nand a little bit about my mother...$k$pBut, I'm sure I'll remember everything\nelse soon enough!"
  },
  {
    "key": "MID_MARC_M_HOME3",
    "value": "Out on patrol? Thanks for working so\nhard! Sometimes just walking around\nlike that can inspire a new strategy.$k$pHave you ever come up with some\namazing new technique while out on\npatrol?"
  },
  {
    "key": "MID_MARC_M_HOME4",
    "value": "You come from another world just like\nme, right? I feel better knowing our\nsituations are similar.$k$pLet's learn about this kingdom\ntogether."
  },
  {
    "key": "MID_MARC_M_HOME5",
    "value": "I was just exploring outside the castle.\nThe geography of this world is just so\nnew, and so exciting!$k$pAnd being near the ruins made me\nfeel like I just might...remember\nsomething..."
  },
  {
    "key": "MID_MARC_M_FRIEND",
    "value": "You're $Nu,\nright? I've come with a great big hello\nfrom $Nf!"
  },
  {
    "key": "MID_MARC_M_LEVEL1",
    "value": "Whew... I'm catching up quick as\nI can, Mother!"
  },
  {
    "key": "MID_MARC_M_LEVEL2",
    "value": "That's a big step closer to\nachieving my dream!"
  },
  {
    "key": "MID_MARC_M_LEVEL3",
    "value": "Hrm... Gotta say, that's kind of a\nletdown."
  },
  {
    "key": "MID_MARC_M_SKILL",
    "value": "This is just like that time I got a\nnew tactics book from my mother!"
  },
  {
    "key": "MID_MARC_M_JOIN",
    "value": "My name's Morgan—son of the\ngenius tactician Robin! Hmm... But\nis my mother around here?"
  },
  {
    "key": "MID_MARC_M_STRONGEST",
    "value": "Oh, so I guess you spotted me! I was\nwatching you from over there, but I\ndidn't think you'd notice...$k$pBut I shouldn't be surprised. I expect\nnothing less from the second\nsmartest tactician I know!$k$pThe smartest tactician I know is my\nown mother, of course. But you could\nbe her rival for sure!$k$pThat's why I've been looking for an\nopportunity to ask to be your\napprentice.$k$pOh, wait! I just let my own plan slip!\nNo way you'd ever take me on as\nyour apprentice now...$k$pHuh? You will? Really?! Oh, thank\nyou! You're amazing! And every bit\nas kind as my mother.$k$pI'm so excited I get to learn all about\ntactics from you. Now that it's official,\nI'll stick to your side like glue!$k$pBecause no matter what happens, I'll\nbelieve in you right up to the end!"
  },
  {
    "key": "MID_MARC_M_VOICE01",
    "value": "はいっ！"
  },
  {
    "key": "MID_MARC_M_VOICE02",
    "value": "Here I go!"
  },
  {
    "key": "MID_MARC_M_VOICE03",
    "value": "うあっ！"
  },
  {
    "key": "MID_MARC_M_VOICE04",
    "value": "N-no..."
  },
  {
    "key": "MID_MARC_M_VOICE05",
    "value": "Checkmate!"
  },
  {
    "key": "MID_MARC_M_VOICE06",
    "value": "Amateur."
  },
  {
    "key": "MID_MARC_M_VOICE07",
    "value": "Just as I planned!"
  },
  {
    "key": "MID_MARC_M_VOICE08",
    "value": "You won't win like that!"
  },
  {
    "key": "MID_MARC_M_VOICE09",
    "value": "Bad move..."
  },
  {
    "key": "MID_MARC_M_VOICE10",
    "value": "Heehee"
  },
  {
    "key": "MID_MARC_M_VOICE11",
    "value": "My mother is the greatest tactician who's ever lived, you know."
  },
  {
    "key": "MID_MARC_M_VOICE12",
    "value": "I've learned a lot watching your tactical style."
  },
  {
    "key": "MID_MARC_M_VOICE13",
    "value": "Would it be OK for me to browse through the Order's library?"
  },
  {
    "key": "MID_MARC_M_VOICE14",
    "value": "Heh. I dug a pitfall nearby—don't tell anyone!"
  },
  {
    "key": "MID_MARC_M_VOICE15",
    "value": "Huh? How'd I wind up with two copies of this strategy book?"
  },
  {
    "key": "MID_MARC_M_VOICE16",
    "value": "Someday, I hope to be a strategist to rival my mother..."
  },
  {
    "key": "MID_MARC_M_VOICE17",
    "value": "I'm glad to be able to help out, even if I've got a lot to learn."
  },
  {
    "key": "MID_MARC_M_VOICE18",
    "value": "OK!"
  },
  {
    "key": "MID_MARC_M_VOICE19",
    "value": "Hmmm..."
  },
  {
    "key": "MID_MARC_M_VOICE20",
    "value": "What's the plan?"
  }
]