[
  {
    "key": "MID_KAIN_HOME1",
    "value": "アリティア王国騎士団の\n名に恥じぬ戦いをしてみせよう！"
  },
  {
    "key": "MID_KAIN_HOME2",
    "value": "おれにはアベルという相棒がいた。\n暴走しがちなおれを、\nアベルは冷静に補佐してくれていたな。"
  },
  {
    "key": "MID_KAIN_HOME3",
    "value": "そうやって城を見回り、\n仲間全員を気にかけているのか。\nさすがだな！"
  },
  {
    "key": "MID_KAIN_HOME4",
    "value": "訓練ならおれもつきあおう！\nこう見えて、騎士見習いたちの\n訓練教官を務めていたこともある。"
  },
  {
    "key": "MID_KAIN_HOME5",
    "value": "はぁっ！\n今は訓練中だ！　用は後で聞こう！\nはぁっ！"
  },
  {
    "key": "MID_KAIN_FRIEND",
    "value": "$Nu殿！\nいずこにおわす！\nわが主からの挨拶の言葉を届けに来た！"
  },
  {
    "key": "MID_KAIN_LEVEL1",
    "value": "よし！\nこれからもやれそうだ！"
  },
  {
    "key": "MID_KAIN_LEVEL2",
    "value": "まあまあだな。\nもっとやれるはずだ…！"
  },
  {
    "key": "MID_KAIN_LEVEL3",
    "value": "これでは\nマルス様に顔向けできん…！"
  },
  {
    "key": "MID_KAIN_SKILL",
    "value": "これがおれの真の力…！\n赤き猛牛の底力、見せてやる！"
  },
  {
    "key": "MID_KAIN_JOIN",
    "value": "おれの名はカイン！\nアリティア王国騎士カインだ！"
  },
  {
    "key": "MID_KAIN_STRONGEST",
    "value": "ジェイガン様に\nよく言われていたのだが…$k$pおれには猪突猛進の\nきらいがあるらしい。$k$pだが、お前がいてくれれば\nおれは戦いの中でも自分を見失わず、\nしっかりと役目を果たせる。$k$pこれもお前のおかげだ。\nありがとう、$Nu。$k$p熱く、そして平静さも失わずに、\nこれからも戦い抜いてみせる…\nそれがおれの望みだ！"
  },
  {
    "key": "MID_KAIN_VOICE01",
    "value": "ふんっ！"
  },
  {
    "key": "MID_KAIN_VOICE02",
    "value": "せぇいっ！"
  },
  {
    "key": "MID_KAIN_VOICE03",
    "value": "うああっ！"
  },
  {
    "key": "MID_KAIN_VOICE04",
    "value": "くそっ…！"
  },
  {
    "key": "MID_KAIN_VOICE05",
    "value": "突撃する！"
  },
  {
    "key": "MID_KAIN_VOICE06",
    "value": "道を開けろ！"
  },
  {
    "key": "MID_KAIN_VOICE07",
    "value": "我こそは！"
  },
  {
    "key": "MID_KAIN_VOICE08",
    "value": "騎士は退かん！"
  },
  {
    "key": "MID_KAIN_VOICE09",
    "value": "無念…だ…"
  },
  {
    "key": "MID_KAIN_VOICE10",
    "value": "はははっ"
  },
  {
    "key": "MID_KAIN_VOICE11",
    "value": "どうかしたか？"
  },
  {
    "key": "MID_KAIN_VOICE12",
    "value": "お、おい…何を"
  },
  {
    "key": "MID_KAIN_VOICE13",
    "value": "一緒に訓練するか？"
  },
  {
    "key": "MID_KAIN_VOICE14",
    "value": "もっと、己を鍛えなければ"
  },
  {
    "key": "MID_KAIN_VOICE15",
    "value": "【猛牛】カイン、と呼ばれていたな"
  },
  {
    "key": "MID_KAIN_VOICE16",
    "value": "俺は俺の全力を尽くす"
  },
  {
    "key": "MID_KAIN_VOICE17",
    "value": "俺が、お前の道を切り拓こう"
  },
  {
    "key": "MID_KAIN_VOICE18",
    "value": "突撃！"
  },
  {
    "key": "MID_KAIN_VOICE19",
    "value": "前進あるのみ！"
  },
  {
    "key": "MID_KAIN_VOICE20",
    "value": "行くぞ！"
  }
]