[
  {
    "key": "MID_CECILIA_HOME1",
    "value": "Anna semble apte à nous diriger.\nNos méthodes sont différentes,\nmais je respecte les siennes."
  },
  {
    "key": "MID_CECILIA_HOME2",
    "value": "J'ai enseigné mes méthodes à\nRoy et Lilina. Tous deux étaient\naussi adorables l'un que l'autre."
  },
  {
    "key": "MID_CECILIA_HOME3",
    "value": "Votre rôle de stratège doit être\népuisant. Que diriez-vous d'une\ntasse de thé pour vous détendre ?"
  },
  {
    "key": "MID_CECILIA_HOME4",
    "value": "Notre amitié m'est précieuse,\nmais je suis avant tout à vos\nordres sur le champ de bataille."
  },
  {
    "key": "MID_CECILIA_HOME5",
    "value": "D'ordinaire, j'enseigne aux autres\nl'art du combat, mais j'aimerais\nbeaucoup apprendre de vous."
  },
  {
    "key": "MID_CECILIA_FRIEND",
    "value": "Ah, $Nu !\nJe m'appelle Cecilia, on m'a\nenvoyée à votre rencontre."
  },
  {
    "key": "MID_CECILIA_LEVEL1",
    "value": "Je suis ravie d'avoir encore tant\nà apprendre !"
  },
  {
    "key": "MID_CECILIA_LEVEL2",
    "value": "Il n'est jamais trop tard pour\napprendre."
  },
  {
    "key": "MID_CECILIA_LEVEL3",
    "value": "Je crains de ne pas mériter mon titre..."
  },
  {
    "key": "MID_CECILIA_SKILL",
    "value": "Je vous remercie de votre confiance."
  },
  {
    "key": "MID_CECILIA_JOIN",
    "value": "Je suis Cecilia, d'Etruria. Êtes-vous\nle stratège de cette armée ? C'est\nun honneur de vous rencontrer."
  },
  {
    "key": "MID_CECILIA_STRONGEST",
    "value": "Quand je suis arrivée ici, je pensais\nvous enseigner mes méthodes,\ncomme je l'ai fait avec Roy et Lilina...$k$pEt puis je vous ai vu vous épanouir\ndans votre rôle de stratège, jusqu'à\nme surpasser.$k$pC'est toujours un moment doux-amer\nde voir la nouvelle génération voler\nde ses propres ailes...$k$pOn se sent un peu... abandonnée.$k$pComment ? Vous avez toujours besoin\nde moi ? Peut-être ai-je encore à vous\napprendre, finalement !$k$pTrès bien, c'est décidé. Je vais rester\nà vos côtés aussi longtemps que\nvous le souhaitez !"
  },
  {
    "key": "MID_CECILIA_VOICE01",
    "value": "はっ！"
  },
  {
    "key": "MID_CECILIA_VOICE02",
    "value": "はぁっ！"
  },
  {
    "key": "MID_CECILIA_VOICE03",
    "value": "きゃああっ！"
  },
  {
    "key": "MID_CECILIA_VOICE04",
    "value": "I let my guard down..."
  },
  {
    "key": "MID_CECILIA_VOICE05",
    "value": "C'est le moment !"
  },
  {
    "key": "MID_CECILIA_VOICE06",
    "value": "Ne me sous-estimez pas."
  },
  {
    "key": "MID_CECILIA_VOICE07",
    "value": "Reculez... ou mourez !"
  },
  {
    "key": "MID_CECILIA_VOICE08",
    "value": "C'est ma chance !"
  },
  {
    "key": "MID_CECILIA_VOICE09",
    "value": "The light..."
  },
  {
    "key": "MID_CECILIA_VOICE10",
    "value": "Heehee"
  },
  {
    "key": "MID_CECILIA_VOICE11",
    "value": "How fare you, tactician?"
  },
  {
    "key": "MID_CECILIA_VOICE12",
    "value": "Now, now... No need to nudge me. You have my attention."
  },
  {
    "key": "MID_CECILIA_VOICE13",
    "value": "I sense a great deal of talent in you. You're a natural."
  },
  {
    "key": "MID_CECILIA_VOICE14",
    "value": "Shall we discuss battle strategy?\n"
  },
  {
    "key": "MID_CECILIA_VOICE15",
    "value": "Should you wish to know anything at all, simply ask!"
  },
  {
    "key": "MID_CECILIA_VOICE16",
    "value": "I will ever do my best to fulfill my role."
  },
  {
    "key": "MID_CECILIA_VOICE17",
    "value": "You have much to teach, and even I have much to learn."
  },
  {
    "key": "MID_CECILIA_VOICE18",
    "value": "Mm-hmm?"
  },
  {
    "key": "MID_CECILIA_VOICE19",
    "value": "Yes?"
  },
  {
    "key": "MID_CECILIA_VOICE20",
    "value": "Your orders."
  }
]