[
  {
    "key": "MID_MARK_PAIR01_HOME1",
    "value": "$nMPID_リン|Je suis ravie que Mark soit avec moi.\nJe ne sais pas si j'aurais pu garder\nmon calme seule dans cet endroit..."
  },
  {
    "key": "MID_MARK_PAIR01_HOME2",
    "value": "$nMPID_リン|Mon père est le chef des Lorca. Il est\nnormal que j'apprenne à monter à\ncheval et à combattre avec les autres !"
  },
  {
    "key": "MID_MARK_PAIR01_HOME3",
    "value": "$nMPID_リン|Je resterai aux côtés de Mark. Si nous\npartons, nous le ferons ensemble !"
  },
  {
    "key": "MID_MARK_PAIR01_HOME4",
    "value": "$nMPID_リン|Vous savez, $GInvocateur,Invocatrice|, vous me\nfaites penser à Mark... Je ne sais pas\npourquoi, c'est juste une impression !"
  },
  {
    "key": "MID_MARK_PAIR01_HOME5",
    "value": "$nMPID_リン|En voyant tous ces héros, je me\ndemande quelles choses incroyables\nont lieu dans leurs mondes !"
  },
  {
    "key": "MID_MARK_PAIR01_FRIEND",
    "value": "$nMPID_リン|$Nf vous envoie\nses amitiés ! Je suis ravie que vous\nvous entendiez bien."
  },
  {
    "key": "MID_MARK_PAIR01_LEVEL1",
    "value": "$nMPID_リン|C'est incroyable, Mark ! Nous faisons\nla paire, comme le vent et les plaines !"
  },
  {
    "key": "MID_MARK_PAIR01_LEVEL2",
    "value": "$nMPID_リン|J'assure vos arrières, Mark !\nConcentrez-vous sur la bataille !"
  },
  {
    "key": "MID_MARK_PAIR01_LEVEL3",
    "value": "$nMPID_リン|Ne vous inquiétez pas, j'ai le\npressentiment que ça ira mieux\nla prochaine fois !"
  },
  {
    "key": "MID_MARK_PAIR01_SKILL",
    "value": "$nMPID_リン|C'est super ! Donnons-nous une\naccolade en guise de remerciements !\nRapprochez-vous, Mark !"
  },
  {
    "key": "MID_MARK_PAIR01_JOIN",
    "value": "Je suis Lyn, et voici Mark, aspirant à\ndevenir stratège ! Vous pouvez vous\naider mutuellement, j'en suis sûre !"
  },
  {
    "key": "MID_MARK_PAIR01_STRONGEST",
    "value": "$nMPID_リン|Voici l'une des lois de Sacae : il faut\nprier la terre et les étoiles chaque\njour, sans exception.$k$pIl y a de nombreuses tribus là-bas.$k$pSi elles unissaient leurs forces, elles\nferaient fuir même les envahisseurs\nles plus terrifiants !$k$pJe brandirais mon épée et je\nme battrais avec les Lorca pour\nprotéger les plaines de Sacae !$k$pOh, je sais. Faisons un pacte, Mark !\nPromettons-nous en tant qu'amis\nque nous nous soutiendrons toujours.$k$pCe sera un engagement officiel entre\nLyn et Mark. Oh, vous pourriez y\nparticiper vous aussi, $GInvocateur,Invocatrice|.$k$pMême si nous oublions notre pacte\nen grandissant, il perdurera !\nPour toujours !"
  },
  {
    "key": "MID_MARK_PAIR01_VOICE01",
    "value": "-"
  },
  {
    "key": "MID_MARK_PAIR01_VOICE02",
    "value": "-"
  },
  {
    "key": "MID_MARK_PAIR01_VOICE03",
    "value": "-"
  },
  {
    "key": "MID_MARK_PAIR01_VOICE04",
    "value": "-"
  },
  {
    "key": "MID_MARK_PAIR01_VOICE09",
    "value": "-"
  },
  {
    "key": "MID_MARK_PAIR01_VOICE05",
    "value": "$nMPID_リン|Nous ne perdrons pas !"
  },
  {
    "key": "MID_MARK_PAIR01_VOICE06",
    "value": "$nMPID_リン|Nous gagnerons ensemble !"
  },
  {
    "key": "MID_MARK_PAIR01_VOICE07",
    "value": "$nMPID_リン|Moi aussi !"
  },
  {
    "key": "MID_MARK_PAIR01_VOICE08",
    "value": "$nMPID_リン|Je sens le vent souffler !"
  },
  {
    "key": "MID_MARK_PAIR01_VOICE10",
    "value": "It can't be..."
  },
  {
    "key": "MID_MARK_PAIR01_VOICE11",
    "value": "Stay strong!"
  },
  {
    "key": "MID_MARK_PAIR01_VOICE12",
    "value": "I've got your back!"
  },
  {
    "key": "MID_MARK_PAIR01_VOICE13",
    "value": "Lend us strength!"
  },
  {
    "key": "MID_MARK_PAIR01_VOICE14",
    "value": "Let's keep it together!"
  },
  {
    "key": "MID_MARK_PAIR01_VOICE15",
    "value": "-"
  },
  {
    "key": "MID_MARK_PAIR01_VOICE16",
    "value": "Let's hold hands so we don't get separated. OK?"
  },
  {
    "key": "MID_MARK_PAIR01_VOICE17",
    "value": "Hmm..."
  },
  {
    "key": "MID_MARK_PAIR01_VOICE18",
    "value": "Swift as the wind!"
  },
  {
    "key": "MID_MARK_PAIR01_VOICE19",
    "value": "All right, let's go!"
  },
  {
    "key": "MID_MARK_PAIR01_VOICE20",
    "value": "$nMPID_リン|Pfiou... Je suis épuisée. Faisons une\npause."
  },
  {
    "key": "MID_MARK_PAIR01_VOICE21",
    "value": "Arriver dans un nouveau monde fut\nune grande surprise pour moi, mais\nje crois que je m'y habitue enfin."
  },
  {
    "key": "MID_MARK_PAIR01_VOICE22",
    "value": "Et vous, Mark ? Oh, ressentez-vous\nla même chose que moi ?"
  },
  {
    "key": "MID_MARK_PAIR01_VOICE23",
    "value": "Je suis ravie d'avoir fait votre\nconnaissance.$k$pSi j'avais été seule, cela aurait sans\ndoute été bien plus difficile à vivre."
  },
  {
    "key": "MID_MARK_PAIR01_VOICE24",
    "value": "Dites-moi, Mark. Vous avez dit\nque vous vouliez étudier la stratégie,\nn'est-ce pas ?"
  },
  {
    "key": "MID_MARK_PAIR01_VOICE25",
    "value": "Mon père et les autres chefs des\nLorca m'apprennent à monter à\ncheval et à combattre."
  },
  {
    "key": "MID_MARK_PAIR01_VOICE26",
    "value": "Si nous avons des ennuis, je veux être\ncapable de combattre à leurs côtés !"
  },
  {
    "key": "MID_MARK_PAIR01_VOICE27",
    "value": "Ne me regardez pas avec cet air\ninquiet ! C'est tout à fait normal pour\nles habitants des plaines de Sacae."
  },
  {
    "key": "MID_MARK_PAIR01_VOICE28",
    "value": "Et puis, ma mère est si douce..."
  },
  {
    "key": "MID_MARK_PAIR01_VOICE29",
    "value": "Je veux la protéger ! Je ne laisserai\npersonne lui faire du mal !"
  },
  {
    "key": "MID_MARK_PAIR01_VOICE30",
    "value": "Hé, pourquoi rigolez-vous ?\nJe suis très forte, vous savez ?"
  },
  {
    "key": "MID_MARK_PAIR01_VOICE31",
    "value": "Un jour, je serai comme mon père,\nun guerrier galopant avec grâce à\ndos de cheval !"
  },
  {
    "key": "MID_MARK_PAIR01_VOICE32",
    "value": "Le moment venu, je vous protégerai\nvous aussi, Mark."
  },
  {
    "key": "MID_MARK_PAIR01_VOICE33",
    "value": "Si vous devenez stratège, vous devrez\négalement prendre part aux combats.\nCela pourrait être dangereux."
  },
  {
    "key": "MID_MARK_PAIR01_VOICE34",
    "value": "Mon père dit toujours qu'en tant\nque guerriers de Sacae, nous devons\ndéfendre la tribu au péril de nos vies."
  },
  {
    "key": "MID_MARK_PAIR01_VOICE35",
    "value": "Vous ne faites pas partie de la tribu,\nmais vous êtes une personne\nimportante pour moi."
  },
  {
    "key": "MID_MARK_PAIR01_VOICE36",
    "value": "Je promets d'être là pour vous, même\nà l'avenir. N'oubliez pas que vous\npourrez toujours compter sur moi."
  }
]